odoo/addons/sale_order_revision/README.rst
odoo/addons/sale_order_revision/__init__.py
odoo/addons/sale_order_revision/__manifest__.py
odoo/addons/sale_order_revision/i18n/ca.po
odoo/addons/sale_order_revision/i18n/de.po
odoo/addons/sale_order_revision/i18n/el_GR.po
odoo/addons/sale_order_revision/i18n/es.po
odoo/addons/sale_order_revision/i18n/es_ES.po
odoo/addons/sale_order_revision/i18n/es_VE.po
odoo/addons/sale_order_revision/i18n/fi.po
odoo/addons/sale_order_revision/i18n/fr.po
odoo/addons/sale_order_revision/i18n/hr.po
odoo/addons/sale_order_revision/i18n/hr_HR.po
odoo/addons/sale_order_revision/i18n/hu.po
odoo/addons/sale_order_revision/i18n/it.po
odoo/addons/sale_order_revision/i18n/nl.po
odoo/addons/sale_order_revision/i18n/nl_NL.po
odoo/addons/sale_order_revision/i18n/pt.po
odoo/addons/sale_order_revision/i18n/pt_BR.po
odoo/addons/sale_order_revision/i18n/ro.po
odoo/addons/sale_order_revision/i18n/sale_order_revision.pot
odoo/addons/sale_order_revision/i18n/sk.po
odoo/addons/sale_order_revision/i18n/sl.po
odoo/addons/sale_order_revision/i18n/tr.po
odoo/addons/sale_order_revision/i18n/tr_TR.po
odoo/addons/sale_order_revision/i18n/vi_VN.po
odoo/addons/sale_order_revision/i18n/zh_CN.po
odoo/addons/sale_order_revision/models/__init__.py
odoo/addons/sale_order_revision/models/sale_order.py
odoo/addons/sale_order_revision/readme/CONTRIBUTORS.rst
odoo/addons/sale_order_revision/readme/DESCRIPTION.rst
odoo/addons/sale_order_revision/readme/INSTALL.rst
odoo/addons/sale_order_revision/static/description/icon.png
odoo/addons/sale_order_revision/static/description/index.html
odoo/addons/sale_order_revision/tests/__init__.py
odoo/addons/sale_order_revision/tests/test_sale_order_revision.py
odoo/addons/sale_order_revision/view/sale_order.xml
odoo13_addon_sale_order_revision-13.0.1.0.1.dev5.dist-info/METADATA
odoo13_addon_sale_order_revision-13.0.1.0.1.dev5.dist-info/WHEEL
odoo13_addon_sale_order_revision-13.0.1.0.1.dev5.dist-info/top_level.txt
odoo13_addon_sale_order_revision-13.0.1.0.1.dev5.dist-info/RECORD
